rcheck/__init__.py
rcheck/check.py
rcheck/check_all.py
rcheck/exceptions.py
rcheck/stubs/__init__.pyi
rcheck/stubs/check.pyi
rcheck/stubs/check_all.pyi
rcheck/stubs/exceptions.pyi
rcheck/stubs/type_utils.pyi
rcheck/type_utils.py
rcheck-0.0.10.dist-info/LICENSE
rcheck-0.0.10.dist-info/METADATA
rcheck-0.0.10.dist-info/WHEEL
rcheck-0.0.10.dist-info/RECORD
